pythonbmp/BITMAPlib.py
pythonbmp/X11colordict.py
pythonbmp/XKCDcolordict.py
pythonbmp/__init__.py
pythonbmp/bmpconstants.py
pythonbmp/bmppal.py
pythonbmp/bufferflip.py
pythonbmp/buffersplit.py
pythonbmp/bufresize.py
pythonbmp/chartools.py
pythonbmp/charts.py
pythonbmp/colordict.py
pythonbmp/colors.py
pythonbmp/conditionaltools.py
pythonbmp/dicttools.py
pythonbmp/fileutils.py
pythonbmp/fonts.py
pythonbmp/fractals.py
pythonbmp/funcmeta.py
pythonbmp/inttools.py
pythonbmp/mathlib.py
pythonbmp/messages.py
pythonbmp/paramchecks.py
pythonbmp/primitives2D.py
pythonbmp/proctimer.py
pythonbmp/shims.py
pythonbmp/solids3D.py
pythonbmp/textgraphics.py
pythonbmp-1.0.5.dist-info/LICENSE
pythonbmp-1.0.5.dist-info/METADATA
pythonbmp-1.0.5.dist-info/WHEEL
pythonbmp-1.0.5.dist-info/top_level.txt
pythonbmp-1.0.5.dist-info/RECORD
