Metadata-Version: 2.1
Name: pythonbmp
Version: 1.0.5
Summary: A pure Python 2D/3D graphics library that outputs to windows bitmap format
Author-email: Joel Alcarez <joelalcarez1975@gmail.com>
License: MIT License
Project-URL: homepage, https://github.com/TechnoTanuki/Python_BMP
Project-URL: documentation, https://github.com/TechnoTanuki/Python_BMP/blob/main/docs/Hello_Graphics.md
Project-URL: repository, https://github.com/TechnoTanuki/Python_BMP
Project-URL: Bug Tracker, https://github.com/TechnoTanuki/Python_BMP/issues
Classifier: Development Status :: 4 - Beta
Classifier: Programming Language :: Python
Requires-Python: >=3.8
License-File: LICENSE
